Metadata-Version: 2.1
Name: BlinkStick310
Version: 1.0.1
Summary: Python package to control BlinkStick USB devices. Unofficial version compatible with Python 3.10 and up
Home-page: http://pypi.python.org/pypi/BlinkStick/
Author: Arvydas Juskevicius
Author-email: arvydas@arvydas.co.uk
License: LICENSE.txt
License-File: LICENSE.txt
